MANIFEST.in
README.md
requirements.txt
setup.cfg
setup.py
bsp_cropper.egg-info/PKG-INFO
bsp_cropper.egg-info/SOURCES.txt
bsp_cropper.egg-info/dependency_links.txt
bsp_cropper.egg-info/entry_points.txt
bsp_cropper.egg-info/requires.txt
bsp_cropper.egg-info/top_level.txt
cropper/__init__.py
cropper/cli.py
cropper/devices.py