Metadata-Version: 1.1
Name: bsp-cropper
Version: 0.2.4
Summary: Crop images for designer sanity
Home-page: https://github.com/frankdilo/cropper-python
Author: Francesco Di Lorenzo
Author-email: fradilorenzo92@gmail.com
License: BSD
Download-URL: https://github.com/frankdilo/cropper-python/tarball/0.2.4
Platform: UNKNOWN
Classifier: Development Status :: 3 - Alpha
Classifier: Intended Audience :: Developers
Classifier: Programming Language :: Python :: 3
